odoo8_addon_web_widget_pattern-8.0.1.0.0-py2.7-nspkg.pth
odoo_addons/web_widget_pattern/__openerp__.py
odoo_addons/web_widget_pattern/__init__.py
odoo_addons/web_widget_pattern/README.rst
odoo_addons/web_widget_pattern/views/templates.xml
odoo_addons/web_widget_pattern/demo/res_partner.xml
odoo_addons/web_widget_pattern/static/description/icon.png
odoo_addons/web_widget_pattern/static/src/js/web_widget_pattern.js
odoo_addons/web_widget_pattern/static/src/css/web_widget_pattern.css
odoo8_addon_web_widget_pattern-8.0.1.0.0.dist-info/top_level.txt
odoo8_addon_web_widget_pattern-8.0.1.0.0.dist-info/WHEEL
odoo8_addon_web_widget_pattern-8.0.1.0.0.dist-info/RECORD
odoo8_addon_web_widget_pattern-8.0.1.0.0.dist-info/metadata.json
odoo8_addon_web_widget_pattern-8.0.1.0.0.dist-info/DESCRIPTION.rst
odoo8_addon_web_widget_pattern-8.0.1.0.0.dist-info/METADATA
odoo8_addon_web_widget_pattern-8.0.1.0.0.dist-info/namespace_packages.txt
